sprockets.mixins.correlation-3.0.0-py3.6-nspkg.pth
sprockets/mixins/__init__.py
sprockets/mixins/correlation/__init__.py
sprockets/mixins/correlation/mixins.py
sprockets.mixins.correlation-3.0.0.dist-info/LICENSE
sprockets.mixins.correlation-3.0.0.dist-info/METADATA
sprockets.mixins.correlation-3.0.0.dist-info/WHEEL
sprockets.mixins.correlation-3.0.0.dist-info/namespace_packages.txt
sprockets.mixins.correlation-3.0.0.dist-info/top_level.txt
sprockets.mixins.correlation-3.0.0.dist-info/zip-safe
sprockets.mixins.correlation-3.0.0.dist-info/RECORD
